testing.py
nutpy/__init__.py
nutpy/constants.py
nutpy/mission.py
nutpy/numeric.py
nutpy/utilities.py
nutpy/algorithms/__init__.py
nutpy/algorithms/visibility.py
nutpy/core/__init__.py
nutpy/core/satellite.py
nutpy/core/kinematics/__init__.py
nutpy/core/kinematics/rotations.py
nutpy/postprocessing/__init__.py
nutpy/postprocessing/pdata.py
nutpy/postprocessing/pgraph.py
nutpy/test/__init__.py
nutpy/test/test_basic.py
nutpy/test/test_numeric.py
nutpy/test/test_rotations.py
nutpy/test/test_utilities.py
nutpy-0.2.3.dist-info/LICENSE.txt
nutpy-0.2.3.dist-info/METADATA
nutpy-0.2.3.dist-info/WHEEL
nutpy-0.2.3.dist-info/top_level.txt
nutpy-0.2.3.dist-info/RECORD
