Metadata-Version: 2.1
Name: nutpy
Version: 0.2.3
Summary: Set of tools to study how space-telescopes with spin-precession scan strategies observe the sky
Author-email: Juan Bermejo <juan.bermejo@protonmail.com>
License: MIT License
Project-URL: homepage, https://gitlab.com/phd-jb/nutpy/nutpy
Project-URL: documentation, https://nutpy.readthedocs.io/
Project-URL: repository, https://gitlab.com/phd-jb/nutpy/nutpy
Project-URL: tracker, https://gitlab.com/phd-jb/nutpy/nutpy/-/issues
Keywords: space,satellite
Classifier: License :: OSI Approved :: MIT License
Classifier: Intended Audience :: Education
Classifier: Intended Audience :: Science/Research
Classifier: Operating System :: OS Independent
Classifier: Programming Language :: Python :: 3
Classifier: Topic :: Scientific/Engineering
Requires-Python: >=3.7
License-File: LICENSE.txt
Requires-Dist: numpy
Requires-Dist: scipy
Requires-Dist: pandas
Requires-Dist: matplotlib
Requires-Dist: tqdm
Requires-Dist: astropy
Requires-Dist: astropy-healpix
Requires-Dist: numba
Provides-Extra: doc
Requires-Dist: sphinx ; extra == 'doc'
Requires-Dist: sphinx-rtd-theme ; extra == 'doc'
Requires-Dist: myst-parser ; extra == 'doc'
Provides-Extra: jupyter
Requires-Dist: notebook ; extra == 'jupyter'
Requires-Dist: ipywidgets >=7.6 ; extra == 'jupyter'
Provides-Extra: test
Requires-Dist: pytest ; extra == 'test'
Requires-Dist: flake8 ; extra == 'test'
Requires-Dist: black ; extra == 'test'
Requires-Dist: mypy ; extra == 'test'
